qyro_sdk/__init__.py
qyro_sdk/auth.py
qyro_sdk/client.py
qyro_sdk/exceptions.py
qyro_sdk/models.py
qyro_sdk/server.py
qyro_sdk-0.2.0.dist-info/licenses/LICENSE
qyro_sdk-0.2.0.dist-info/METADATA
qyro_sdk-0.2.0.dist-info/WHEEL
qyro_sdk-0.2.0.dist-info/top_level.txt
qyro_sdk-0.2.0.dist-info/RECORD
