Metadata-Version: 2.4
Name: qyro-sdk
Version: 0.2.0
Summary: Python SDK for Qyro assistant session + chat API
Author: Generated
License: MIT
Requires-Python: >=3.8
License-File: LICENSE
Requires-Dist: requests
Requires-Dist: PyJWT
Dynamic: license-file
